decouple_nacl.py
decouple_nacl_tyokalut.py
python_decouple_nacl-0.2.dist-info/METADATA
python_decouple_nacl-0.2.dist-info/WHEEL
python_decouple_nacl-0.2.dist-info/historia.json
python_decouple_nacl-0.2.dist-info/top_level.txt
python_decouple_nacl-0.2.dist-info/RECORD
