Metadata-Version: 2.4
Name: python-decouple-nacl
Version: 0.2
Summary: Asymmetrisen salauksen tuki python-decouple-pakettiin
Author-email: Antti Hautaniemi <antti.hautaniemi@pispalanit.fi>
License: MIT
Project-URL: Repository, https://github.com/an7oine/python-decouple-nacl.git
Requires-Python: >=3.8
Requires-Dist: PyNaCl
Requires-Dist: python-decouple
